[{
    "imageURL": "http://www.dogster.com/wp-content/uploads/2015/05/Cute%20dog%20listening%20to%20music%201_1.jpg",
    "imageDescription": "A smiling golden-brown golden retreiver listening to music.",
    "name": "Zeus",
    "sex": "Male",
    "age": "3",
    "breed": "Golden Retriever",
    "story": "Owner Passed away"
  },
  {
    "imageURL": "https://www.cesarsway.com/dog-behavior/innocuous-behaviors/common-dog-behaviors-explained",
    "imageDescription": "abcdefghijklmnopqrstuvwxyz",
    "name": "Cesar",
    "sex": "Male",
    "age": "3",
    "breed": "unknown",
    "story": "abcdefghijklmnopqrstuvwxyz"
  },
  {
    "imageURL": "https://www.nationalgeographic.com/animals/mammals/d/domestic-dog/",
    "imageDescription": "abcdefghijklmnopqrstuvwxyz",
    "name": "Diamond",
    "sex": "Female",
    "age": "4",
    "breed": "Golden Retriever/Rottweiler",
    "story": "abcdefghijklmnopqrstuvwxyz"
  },
  {
    "imageURL": "http://marshallspetzone.blogspot.com/2017/03/rottweiler-of-most-misunderstood-breed.html",
    "imageDescription": "abcdefghijklmnopqrstuvwxyz",
    "name": "Princess",
    "sex": "Female",
    "age": "4",
    "breed": "Golden Retriever/Rottweiler",
    "story": "abcdefghijklmnopqrstuvwxyz"
  },
  {
    "imageURL": "https://www.pocketpitbull.com/american-pitbull-terrier-need-know/",
    "imageDescription": "abcdefghijklmnopqrstuvwxyz",
    "name": "Royce",
    "sex": "Male",
    "age": "2",
    "breed": "Shaggy",
    "story": "abcdefghijklmnopqrstuvwxyz"
  }
]